{"ac":[{"postime":"1598246997337","icao":"A73E34","reg":"N566LF","type":"A119","wtc":"1","spd":"147.5","altt":"0","alt":"1700","galt":"1680","talt":"","lat":"45.215652","lon":"-122.913666","vsit":"0","vsi":"704","trkh":"0","ttrk":"","trak":"254.3","sqk":"0316","call":"N566LF","gnd":"0","trt":"5","pos":"1","mlat":"0","tisb":"0","sat":"0","opicao":"","cou":"United States","mil":"0","interested":"1","dst":"20.07"},{"postime":"1598246997164","icao":"A6746A","reg":"N515ED","type":"C172","wtc":"1","spd":"87","altt":"0","alt":"8525","galt":"8496","talt":"","lat":"45.338249","lon":"-122.455355","vsit":"1","vsi":"64","trkh":"0","ttrk":"","trak":"226.4","sqk":"3560","call":"N515ED","gnd":"0","trt":"2","pos":"1","mlat":"0","tisb":"0","sat":"0","opicao":"","cou":"United States","mil":"0","interested":"0","dst":"13.63"},{"postime":"1598246997163","icao":"A54F77","reg":"N441MR","type":"R44","wtc":"1","spd":"84.7","altt":"0","alt":"1200","galt":"1180","talt":"","lat":"45.349274","lon":"-122.767966","vsit":"1","vsi":"64","trkh":"0","ttrk":"","trak":"191.6","sqk":"1200","call":"N441MR","gnd":"0","trt":"5","pos":"1","mlat":"0","tisb":"0","sat":"0","opicao":"","cou":"United States","mil":"0","interested":"0","dst":"10.14"},{"postime":"1598246997926","icao":"A81316","reg":"N6194E","type":"C172","wtc":"1","spd":"105.5","altt":"0","alt":"2950","galt":"2960","talt":"","lat":"45.537539","lon":"-122.346899","vsit":"0","vsi":"128","trkh":"0","ttrk":"189.8","trak":"201.7","sqk":"0173","call":"N6194E","gnd":"0","trt":"5","pos":"1","mlat":"0","tisb":"0","sat":"0","opicao":"","cou":"United States","mil":"0","interested":"0","dst":"13.93"},{"postime":"1598246995652","icao":"A07EE3","reg":"N13096","type":"C172","wtc":"1","spd":"120.1","altt":"0","alt":"4425","galt":"4435","talt":"2496","lat":"45.824249","lon":"-122.68781","vsit":"0","vsi":"0","trkh":"0","ttrk":"160.3","trak":"165","sqk":"3537","call":"N13096","gnd":"0","trt":"5","pos":"1","mlat":"0","tisb":"0","sat":"0","opicao":"","cou":"United States","mil":"0","interested":"0","dst":"19.16"},{"postime":"1598246973475","icao":"A82DFB","reg":"N626QX","type":"E75L","wtc":"2","spd":"14.2","altt":"0","alt":"50","galt":"40","talt":"4224","lat":"45.592026","lon":"-122.598529","vsit":"0","vsi":"64","trkh":"1","ttrk":"","trak":"208.1","sqk":"7217","call":"QXE2568","gnd":"1","trt":"5","pos":"1","mlat":"0","tisb":"0","sat":"0","opicao":"QXE","cou":"United States","mil":"0","interested":"0","from":"KSEA Seattle Tacoma United States","to":"CYEG Edmonton Canada","dst":"6.13"}],"total":6,"ctime":1598247001683,"ptime":33}