{"ac":[{"postime":"1596353400084","icao":"A6A5E7","reg":"N5274V","type":"C172","wtc":"1","spd":"67.6","altt":"0","alt":"475","galt":"625","talt":"2016","lat":"45.572267","lon":"-122.53347","vsit":"0","vsi":"-384","trkh":"0","ttrk":"","trak":"262.3","sqk":"0171","call":"N5274V","gnd":"0","trt":"5","pos":"1","mlat":"0","tisb":"0","sat":"0","opicao":"","cou":"United States","mil":"0","interested":"0","dst":"7.18"},{"postime":"1596353398882","icao":"A98789","reg":"N713DM","type":"S22T","wtc":"1","spd":"85.1","altt":"0","alt":"400","galt":"550","talt":"1216","lat":"45.233139","lon":"-122.784707","vsit":"0","vsi":"-576","trkh":"0","ttrk":"","trak":"107.8","sqk":"1200","call":"N713DM","gnd":"0","trt":"5","pos":"1","mlat":"0","tisb":"0","sat":"0","opicao":"","cou":"United States","mil":"0","interested":"0","dst":"16.96"}],"total":2,"ctime":1596353401797,"ptime":66}